malmo/MalmoPython.lib
malmo/MalmoPython.pyd
malmo/__init__.py
malmo/__main__.py
malmo/dummy.cp36-win_amd64.pyd
malmo/launch_minecraft_in_background.py
malmo/malmoutils.py
malmo/minecraftbootstrap.py
malmo/run_mission.py
malmo/version.py
malmo-0.36.0.0.dist-info/LICENSE.txt
malmo-0.36.0.0.dist-info/METADATA
malmo-0.36.0.0.dist-info/RECORD
malmo-0.36.0.0.dist-info/WHEEL
malmo-0.36.0.0.dist-info/top_level.txt
