Metadata-Version: 2.1
Name: malmo
Version: 0.36.0.0
Summary: Project Malmo is a platform for Artificial Intelligence experimentation and research built on top of Minecraft
Home-page: https://github.com/Microsoft/malmo
Author: Microsoft
Author-email: v-andkra@microsoft.com
License: UNKNOWN
Keywords: AI Minecraft Reinforcement-Learning
Platform: UNKNOWN
Classifier: Development Status :: 4 - Beta
Classifier: Intended Audience :: Developers
Classifier: Topic :: Scientific/Engineering :: Artificial Intelligence
Classifier: License :: OSI Approved :: MIT License
Classifier: Programming Language :: Python :: 3.4
Classifier: Programming Language :: Python :: 3.5
Classifier: Programming Language :: Python :: 3.6
Provides-Extra: dev
Requires-Dist: check-manifest; extra == 'dev'
Provides-Extra: test
Requires-Dist: coverage; extra == 'test'
